kps_api/__init__.py
kps_api/api_client.py
kps_api/configuration.py
kps_api/rest.py
kps_api/api/__init__.py
kps_api/api/application_api.py
kps_api/api/application_status_api.py
kps_api/api/auditlog_api.py
kps_api/api/auth_api.py
kps_api/api/category_api.py
kps_api/api/certificate_api.py
kps_api/api/cloud_profile_api.py
kps_api/api/connector_class_api.py
kps_api/api/connector_config_api.py
kps_api/api/connector_instance_api.py
kps_api/api/connector_stream_api.py
kps_api/api/container_registry_api.py
kps_api/api/data_pipeline_api.py
kps_api/api/data_source_api.py
kps_api/api/event_api.py
kps_api/api/function_api.py
kps_api/api/helm_api.py
kps_api/api/http_service_proxy_api.py
kps_api/api/kiali_api.py
kps_api/api/kubernetes_cluster_api.py
kps_api/api/log_api.py
kps_api/api/log_collector_api.py
kps_api/api/ml_model_api.py
kps_api/api/ml_model_status_api.py
kps_api/api/node_api.py
kps_api/api/node_info_api.py
kps_api/api/project_api.py
kps_api/api/runtime_environment_api.py
kps_api/api/service_binding_api.py
kps_api/api/service_class_api.py
kps_api/api/service_domain_api.py
kps_api/api/service_domain_cluster_api.py
kps_api/api/service_domain_info_api.py
kps_api/api/service_instance_api.py
kps_api/api/ssh_api.py
kps_api/api/storage_profile_api.py
kps_api/api/user_api.py
kps_api/api/user_api_token_api.py
kps_api/api/user_public_key_api.py
kps_api/models/__init__.py
kps_api/models/additional_item.py
kps_api/models/address.py
kps_api/models/addresses.py
kps_api/models/aggregate_info.py
kps_api/models/aggregate_spec.py
kps_api/models/aggregation.py
kps_api/models/ai_inferencing_runtime.py
kps_api/models/ai_inferencing_service_profile.py
kps_api/models/api_error_payload.py
kps_api/models/app.py
kps_api/models/app_health.py
kps_api/models/app_list.py
kps_api/models/app_list_item.py
kps_api/models/app_overview.py
kps_api/models/app_status.py
kps_api/models/application.py
kps_api/models/application_containers.py
kps_api/models/application_containers_base_object.py
kps_api-1.3.10.dist-info/METADATA
kps_api-1.3.10.dist-info/WHEEL
kps_api-1.3.10.dist-info/top_level.txt
kps_api-1.3.10.dist-info/RECORD
