Metadata-Version: 2.1
Name: kps-api
Version: 1.3.10
Summary: Nutanix Karbon Platform Services Python SDK
Home-page: https://github.com/nutanix/karbon-platform-services/tree/master/sdk/python
Author-email: karbon-platform-services-api@nutanix.com
License: UNKNOWN
Keywords: Swagger,Karbon Platform Services API reference.
Platform: UNKNOWN
Requires-Dist: urllib3 (>=1.15)
Requires-Dist: six (>=1.10)
Requires-Dist: certifi
Requires-Dist: python-dateutil
